{
    "productListXML": {
       "product_list": [
          {
             "id": "1",
             "name": "Product 1",
             "price": "4.0",
             "qtyOnHand": "100"
          },
          {
             "id": "2",
             "name": "Product 2",
             "price": "8.0",
             "qtyOnHand": "200"
          },
          {
             "id": "3",
             "name": "Product 3",
             "price": "12.0",
             "qtyOnHand": "300"
          },
          {
             "id": "4",
             "name": "Product 4",
             "price": "16.0",
             "qtyOnHand": "400"
          },
          {
             "id": "5",
             "name": "Product 5",
             "price": "20.0",
             "qtyOnHand": "500"
          },
          {
             "id": "6",
             "name": "Product 6",
             "price": "24.0",
             "qtyOnHand": "600"
          },
          {
             "id": "7",
             "name": "Product 7",
             "price": "28.0",
             "qtyOnHand": "700"
          },
          {
             "id": "8",
             "name": "Product 8",
             "price": "32.0",
             "qtyOnHand": "800"
          },
          {
             "id": "9",
             "name": "Product 9",
             "price": "36.0",
             "qtyOnHand": "900"
          },
          {
             "id": "10",
             "name": "Product 10",
             "price": "40.0",
             "qtyOnHand": "1000"
          },
          {
             "id": "11",
             "name": "Product 11",
             "price": "14.0",
             "qtyOnHand": "100"
          },
          {
             "id": "12",
             "name": "Product 12",
             "price": "12.0",
             "qtyOnHand": "20"
          }
       ]
    }
 }